autopd/__init__.py
autopd/advanced/__init__.py
autopd/advanced/adversarial_robustness_analyzer.py
autopd/advanced/anomaly_activated_alert_system.py
autopd/advanced/autonomous_optimization_loop_injection.py
autopd/advanced/causal_fault_tree_analysis.py
autopd/advanced/dna_tracker.py
autopd/advanced/federated_training_synchronization_monitor.py
autopd/advanced/hardware_aware_learning_curve_forecasting.py
autopd/advanced/integration.py
autopd/advanced/latent_loss_surface_mapping.py
autopd/advanced/llm_connected_think_tank.py
autopd/advanced/neuro_behavioral_pattern_clustering.py
autopd/advanced/quantum_inspired_optimization_pathfinder.py
autopd/advanced/real_time_model_cognition.py
autopd/advanced/synthetic_model_shadowing.py
autopd/bottleneck/__init__.py
autopd/bottleneck/failure_forecaster.py
autopd/core/__init__.py
autopd/core/doctor.py
autopd/integrations/__init__.py
autopd/integrations/deepspeed_integration.py
autopd/integrations/huggingface_integration.py
autopd/integrations/lightning_integration.py
autopd/integrations/pytorch_integration.py
autopd/llm/__init__.py
autopd/llm/llm_interface.py
autopd/memory/__init__.py
autopd/memory/experience_brain.py
autopd/profiler/__init__.py
autopd/profiler/dataloader_profiler.py
autopd/profiler/gradient_profiler.py
autopd/profiler/hardware_profiler.py
autopd/profiler/memory_profiler.py
autopd/profiler/timing_profiler.py
autopd/suggestion/__init__.py
autopd/suggestion/optimization_advisor.py
autopd/utils/__init__.py
autopd/visualizer/__init__.py
autopd/visualizer/visualizer.py
autopd-0.1.1.dist-info/licenses/LICENSE
autopd-0.1.1.dist-info/METADATA
autopd-0.1.1.dist-info/WHEEL
autopd-0.1.1.dist-info/entry_points.txt
autopd-0.1.1.dist-info/top_level.txt
autopd-0.1.1.dist-info/RECORD
