Metadata-Version: 2.4
Name: autopd
Version: 0.1.1
Summary: AutoPipelineDoctor: AI-powered monitoring, diagnosis, and optimization for ML/AI pipelines
Home-page: https://github.com/autopipelinedoctor/autopd
Author: AutoPipelineDoctor Team
Author-email: info@autopipelinedoctor.ai
Project-URL: Bug Tracker, https://github.com/autopipelinedoctor/autopd/issues
Project-URL: Documentation, https://autopipelinedoctor.ai/docs
Project-URL: Source Code, https://github.com/autopipelinedoctor/autopd
Keywords: machine learning,deep learning,monitoring,optimization,diagnosis,pytorch,tensorflow,jax,pipeline,AI,ML
Classifier: Development Status :: 4 - Beta
Classifier: Intended Audience :: Developers
Classifier: Intended Audience :: Science/Research
Classifier: License :: OSI Approved :: MIT License
Classifier: Programming Language :: Python :: 3
Classifier: Programming Language :: Python :: 3.8
Classifier: Programming Language :: Python :: 3.9
Classifier: Programming Language :: Python :: 3.10
Classifier: Programming Language :: Python :: 3.11
Classifier: Topic :: Scientific/Engineering :: Artificial Intelligence
Classifier: Topic :: Software Development :: Libraries :: Python Modules
Classifier: Topic :: System :: Monitoring
Requires-Python: >=3.8
License-File: LICENSE
Requires-Dist: numpy>=1.20.0
Requires-Dist: pandas>=1.3.0
Requires-Dist: matplotlib>=3.4.0
Requires-Dist: plotly>=5.0.0
Requires-Dist: torch>=1.9.0
Requires-Dist: psutil>=5.8.0
Requires-Dist: gputil>=1.4.0
Requires-Dist: py-cpuinfo>=8.0.0
Requires-Dist: pynvml>=11.0.0
Requires-Dist: tqdm>=4.60.0
Requires-Dist: dash>=2.0.0
Requires-Dist: seaborn>=0.11.0
Requires-Dist: scikit-learn>=1.0.0
Requires-Dist: scipy>=1.7.0
Provides-Extra: lightning
Requires-Dist: pytorch-lightning>=1.5.0; extra == "lightning"
Provides-Extra: huggingface
Requires-Dist: transformers>=4.5.0; extra == "huggingface"
Provides-Extra: deepspeed
Requires-Dist: deepspeed>=0.5.0; extra == "deepspeed"
Provides-Extra: llm
Requires-Dist: transformers>=4.5.0; extra == "llm"
Requires-Dist: openai>=0.27.0; extra == "llm"
Requires-Dist: anthropic>=0.3.0; extra == "llm"
Provides-Extra: viz
Requires-Dist: dash>=2.0.0; extra == "viz"
Requires-Dist: seaborn>=0.11.0; extra == "viz"
Requires-Dist: bokeh>=2.4.0; extra == "viz"
Provides-Extra: advanced
Requires-Dist: scikit-learn>=1.0.0; extra == "advanced"
Requires-Dist: scipy>=1.7.0; extra == "advanced"
Requires-Dist: networkx>=2.6.0; extra == "advanced"
Requires-Dist: statsmodels>=0.13.0; extra == "advanced"
Requires-Dist: umap-learn>=0.5.0; extra == "advanced"
Requires-Dist: hdbscan>=0.8.0; extra == "advanced"
Requires-Dist: pyro-ppl>=1.7.0; extra == "advanced"
Requires-Dist: pygraphviz>=1.7; extra == "advanced"
Requires-Dist: qiskit>=0.30.0; extra == "advanced"
Requires-Dist: pennylane>=0.20.0; extra == "advanced"
Requires-Dist: torchviz>=0.0.2; extra == "advanced"
Requires-Dist: optuna>=2.10.0; extra == "advanced"
Requires-Dist: ray[tune]>=1.13.0; extra == "advanced"
Requires-Dist: tensorboardX>=2.5.0; extra == "advanced"
Provides-Extra: dev
Requires-Dist: pytest>=6.0.0; extra == "dev"
Requires-Dist: pytest-cov>=2.12.0; extra == "dev"
Requires-Dist: black>=21.5b2; extra == "dev"
Requires-Dist: isort>=5.9.0; extra == "dev"
Requires-Dist: mypy>=0.812; extra == "dev"
Requires-Dist: flake8>=3.9.0; extra == "dev"
Requires-Dist: sphinx>=4.0.0; extra == "dev"
Requires-Dist: sphinx-rtd-theme>=0.5.0; extra == "dev"
Requires-Dist: twine>=3.4.0; extra == "dev"
Requires-Dist: build>=0.7.0; extra == "dev"
Provides-Extra: all
Requires-Dist: pytorch-lightning>=1.5.0; extra == "all"
Requires-Dist: transformers>=4.5.0; extra == "all"
Requires-Dist: deepspeed>=0.5.0; extra == "all"
Requires-Dist: openai>=0.27.0; extra == "all"
Requires-Dist: anthropic>=0.3.0; extra == "all"
Requires-Dist: bokeh>=2.4.0; extra == "all"
Requires-Dist: networkx>=2.6.0; extra == "all"
Requires-Dist: statsmodels>=0.13.0; extra == "all"
Requires-Dist: umap-learn>=0.5.0; extra == "all"
Requires-Dist: hdbscan>=0.8.0; extra == "all"
Dynamic: author
Dynamic: author-email
Dynamic: classifier
Dynamic: description
Dynamic: description-content-type
Dynamic: home-page
Dynamic: keywords
Dynamic: license-file
Dynamic: project-url
Dynamic: provides-extra
Dynamic: requires-dist
Dynamic: requires-python
Dynamic: summary
